scrapy_utils/__init__.py
scrapy_utils/extensions.py
scrapy_utils/loaders.py
scrapy_utils/processors.py
scrapy_utils/request.py
scrapy_utils-0.0.6.dist-info/DESCRIPTION.rst
scrapy_utils-0.0.6.dist-info/METADATA
scrapy_utils-0.0.6.dist-info/RECORD
scrapy_utils-0.0.6.dist-info/WHEEL
scrapy_utils-0.0.6.dist-info/metadata.json
scrapy_utils-0.0.6.dist-info/top_level.txt
